pogema/__init__.py
pogema/a_star_policy.py
pogema/envs.py
pogema/generator.py
pogema/grid.py
pogema/grid_config.py
pogema/grid_registry.py
pogema/utils.py
pogema/integrations/__init__.py
pogema/integrations/make_pogema.py
pogema/integrations/pettingzoo.py
pogema/integrations/pymarl.py
pogema/integrations/sample_factory.py
pogema/svg_animation/__init__.py
pogema/svg_animation/animation_drawer.py
pogema/svg_animation/animation_wrapper.py
pogema/svg_animation/svg_objects.py
pogema/wrappers/__init__.py
pogema/wrappers/metrics.py
pogema/wrappers/multi_time_limit.py
pogema/wrappers/persistence.py
pogema-1.4.0.dist-info/LICENSE
pogema-1.4.0.dist-info/METADATA
pogema-1.4.0.dist-info/WHEEL
pogema-1.4.0.dist-info/top_level.txt
pogema-1.4.0.dist-info/RECORD
