Metadata-Version: 2.1
Name: pogema
Version: 1.4.0
Summary: Partially Observable Grid Environment for Multiple Agents
Home-page: https://github.com/Cognitive-AI-Systems/pogema
Author: Alexey Skrynnik
License: MIT
Requires-Python: >=3.8,<3.13
License-File: LICENSE
Requires-Dist: gymnasium==0.28.1
Requires-Dist: numpy<=1.26.4,>1.23.5
Requires-Dist: pydantic<=1.9.1,>=1.8.2
